{"project#1":{"record-id":1,"name":"Project#1-Name","scrum-master":"Project#1-Scrum-Master-Name","description":"Project#1-Description","team-members":{"Team-Member-1":{"name":"Project#1-Team-Member-1-Name","member-id":1,"member-designation":"Project#1-Team-Member-1-Designation"},"Team-Member-2":{"name":"Project#1-Team-Member-2-Name","member-id":2,"member-designation":"Project#1-Team-Member-2-Designation"},"Team-Member-3":{"name":"Project#1-Team-Member-3-Name","member-id":3,"member-designation":"Project#1-Team-Member-3-Designation"}}},"project#2":{"record-id":2,"name":"Project#2-Name","scrum-master":"Project#2-Scrum-Master-Name","description":"Project#2-Description","team-members":{"Team-Members-1":{"name":"Project#2-Team-Member-1-Name","member-id":4,"member-designation":"Project#2-Team-Member-1-Designation"},"Team-Members-2":{"name":"Project#2-Team-Member-2-Name","member-id":5,"member-designation":"Project#2-Team-Member-2-Designation"}}},"project#3":{"record-id":3,"name":"Project#3-Name","scrum-master":"Project#3-Scrum-Master-Name","description":"Project#3-Description","team-members":{"Team-Member-1":{"name":"Project#3-Team-Member-1-Name","member-id":6,"member-designation":"Project#3-Team-Member-1-Designation"},"Team-Member-2":{"name":"Project#3-Team-Member-2-Name","member-id":7,"member-designation":"Project#3-Team-Member-2-Designation"},"Team-Member-3":{"name":"Project#3-Team-Member-3-Name","member-id":8,"member-designation":"Project#3-Team-Member-3-Designation"}}},"project#4":{"project#4":{"record-id":4,"name":"Project#4-Name","scrum-master":"Project#4-Scrum-Master-Name","description":"Project#4-Description","team-members":{"Team-Member-1":{"name":"Project#4-Team-Member-1-Name","member-id":9,"member-designation":"Project#4-Team-Member-1-Designation"},"Team-Member-2":{"name":"Project#4-Team-Member-2-Name","member-id":10,"member-designation":"Project#4-Team-Member-2-Designation"},"Team-Member-3":{"name":"Project#4-Team-Member-3-Name","member-id":11,"member-designation":"Project#4-Team-Member-3-Designation"}}}}}